pkapredict/RDkit_descriptors.py
pkapredict/__init__.py
pkapredict/data_preprocessing.py
pkapredict/load_model.py
pkapredict/plotting.py
pkapredict/predict_pKa.py
pkapredict/smiles_to_rdkit_descriptors.py
pkapredict/models/best_pKa_model.pkl
pkapredict-0.2.0.dist-info/METADATA
pkapredict-0.2.0.dist-info/WHEEL
pkapredict-0.2.0.dist-info/licenses/LICENSE
pkapredict-0.2.0.dist-info/RECORD
